azure/mgmt/storagesync/__init__.py
azure/mgmt/storagesync/_configuration.py
azure/mgmt/storagesync/_microsoft_storage_sync.py
azure/mgmt/storagesync/_version.py
azure/mgmt/storagesync/aio/__init__.py
azure/mgmt/storagesync/aio/_configuration.py
azure/mgmt/storagesync/aio/_microsoft_storage_sync.py
azure/mgmt/storagesync/aio/operations/__init__.py
azure/mgmt/storagesync/aio/operations/_cloud_endpoints_operations.py
azure/mgmt/storagesync/aio/operations/_operation_status_operations.py
azure/mgmt/storagesync/aio/operations/_operations.py
azure/mgmt/storagesync/aio/operations/_private_endpoint_connections_operations.py
azure/mgmt/storagesync/aio/operations/_private_link_resources_operations.py
azure/mgmt/storagesync/aio/operations/_registered_servers_operations.py
azure/mgmt/storagesync/aio/operations/_server_endpoints_operations.py
azure/mgmt/storagesync/aio/operations/_storage_sync_services_operations.py
azure/mgmt/storagesync/aio/operations/_sync_groups_operations.py
azure/mgmt/storagesync/aio/operations/_workflows_operations.py
azure/mgmt/storagesync/models/__init__.py
azure/mgmt/storagesync/models/_microsoft_storage_sync_enums.py
azure/mgmt/storagesync/models/_models.py
azure/mgmt/storagesync/models/_models_py3.py
azure/mgmt/storagesync/operations/__init__.py
azure/mgmt/storagesync/operations/_cloud_endpoints_operations.py
azure/mgmt/storagesync/operations/_operation_status_operations.py
azure/mgmt/storagesync/operations/_operations.py
azure/mgmt/storagesync/operations/_private_endpoint_connections_operations.py
azure/mgmt/storagesync/operations/_private_link_resources_operations.py
azure/mgmt/storagesync/operations/_registered_servers_operations.py
azure/mgmt/storagesync/operations/_server_endpoints_operations.py
azure/mgmt/storagesync/operations/_storage_sync_services_operations.py
azure/mgmt/storagesync/operations/_sync_groups_operations.py
azure/mgmt/storagesync/operations/_workflows_operations.py
azure_mgmt_storagesync-1.0.0.dist-info/METADATA
azure_mgmt_storagesync-1.0.0.dist-info/WHEEL
azure_mgmt_storagesync-1.0.0.dist-info/top_level.txt
azure_mgmt_storagesync-1.0.0.dist-info/RECORD
